pyavcontrol/__init__.py
pyavcontrol/client/__init__.py
pyavcontrol/client/async_client.py
pyavcontrol/client/base.py
pyavcontrol/client/sync_client.py
pyavcontrol/config.py
pyavcontrol/connection/__init__.py
pyavcontrol/connection/async_connection.py
pyavcontrol/connection/sync_connection.py
pyavcontrol/const.py
pyavcontrol/core.py
pyavcontrol/data/future/acurus_m8.yaml
pyavcontrol/data/future/anthem_d2v.yaml
pyavcontrol/data/future/classe_ssp600.yaml
pyavcontrol/data/future/lyngdorf_mp60.yaml
pyavcontrol/data/future/marantz_av8805.yaml
pyavcontrol/data/future/monoprice_6.yaml
pyavcontrol/data/src/classe_omicron.yaml
pyavcontrol/data/src/hdfury_vrroom.yaml
pyavcontrol/data/src/jbl_sdp75.yaml
pyavcontrol/data/src/lyngdorf_cd2.yaml
pyavcontrol/data/src/lyngdorf_tdai3400.yaml
pyavcontrol/data/src/mcintosh_legacy.yaml
pyavcontrol/data/src/mcintosh_mx160.yaml
pyavcontrol/data/src/mcintosh_mx170.yaml
pyavcontrol/data/src/mcintosh_mx180.yaml
pyavcontrol/data/src/trinnov_altitude16.yaml
pyavcontrol/data/src/trinnov_altitude32.yaml
pyavcontrol/data/src/xantech_mx88_audio.yaml
pyavcontrol/data/src/xantech_mx88_video.yaml
pyavcontrol/helper.py
pyavcontrol/library/README.md
pyavcontrol/library/__init__.py
pyavcontrol/library/docs.py
pyavcontrol/library/model.py
pyavcontrol/library/schema.py
pyavcontrol/library/yaml_library.py
pyavcontrol/library_flat/README.md
pyavcontrol-0.1.3.dist-info/LICENSE
pyavcontrol-0.1.3.dist-info/METADATA
pyavcontrol-0.1.3.dist-info/WHEEL
pyavcontrol-0.1.3.dist-info/RECORD
