Metadata-Version: 2.1
Name: pyavcontrol
Version: 0.1.3
Summary: Python Control of Audio/Visual Equipment (RS232/IP)
License: LICENSE
Author: Ryan Snodgrass
Author-email: rsnodgrass@gmail.com
Requires-Python: >=3.10,<4.0
Classifier: License :: Other/Proprietary License
Classifier: Programming Language :: Python :: 3
Classifier: Programming Language :: Python :: 3.10
Classifier: Programming Language :: Python :: 3.11
Classifier: Programming Language :: Python :: 3.12
Requires-Dist: pyserial (>=3.5,<4.0)
Requires-Dist: pyserial-asyncio (>=0.6,<0.7)
Requires-Dist: pyyaml (>=6.0.1,<7.0.0)
Requires-Dist: ratelimit (>=2.2.1,<3.0.0)
